robhan_cdk_lib/utils/_jsii/__init__.py
robhan_cdk_lib/utils/_jsii/utils@0.0.160.jsii.tgz
robhan_cdk_lib_utils-0.0.160.dist-info/LICENSE
robhan_cdk_lib_utils-0.0.160.dist-info/METADATA
robhan_cdk_lib_utils-0.0.160.dist-info/WHEEL
robhan_cdk_lib_utils-0.0.160.dist-info/top_level.txt
robhan_cdk_lib_utils-0.0.160.dist-info/RECORD
